LICENSE
MANIFEST.in
README.md
manage.py
setup.py
requests_tracker/__init__.py
requests_tracker/admin.py
requests_tracker/apps.py
requests_tracker/exceptions.py
requests_tracker/http_methods.py
requests_tracker/models.py
requests_tracker/monkey.py
requests_tracker/states.py
requests_tracker/filtering/__init__.py
requests_tracker/filtering/categories.py
requests_tracker/filtering/columns.py
requests_tracker/filtering/filters.py
requests_tracker/filtering/handlers.py
requests_tracker/migrations/0001_initial.py
requests_tracker/migrations/__init__.py
requests_tracker/requests/__init__.py
requests_tracker/requests/sessions.py
requests_tracker/signals/__init__.py
requests_tracker/signals/handlers.py
requests_tracker/templates/requests_tracker/request.tmpl
requests_tracker/templates/requests_tracker/response.tmpl
requests_tracker/utils/__init__.py
requests_tracker/utils/collections.py
requests_tracker/utils/http_message.py
requests_tracker/utils/unique.py
testapp/__init__.py
testapp/settings.py
testapp/urls.py
testapp/wsgi.py
tests/__init__.py