Metadata-Version: 1.1
Name: django-requests-tracker
Version: 2.10.4
Summary: Tracking http requests send by python-requests inside a Django application
Home-page: https://sveinchen.github.io/django-requests-tracker
Author: sveinchen
Author-email: sveinchen@gmail.com
License: UNKNOWN
Platform: UNKNOWN
Classifier: Development Status :: 4 - Beta
Classifier: Environment :: Web Environment
Classifier: Framework :: Django
Classifier: Framework :: Django :: 1.8
Classifier: Framework :: Django :: 1.9
Classifier: Framework :: Django :: 1.10
Classifier: Intended Audience :: Developers
Classifier: License :: OSI Approved :: MIT License
Classifier: Operating System :: OS Independent
Classifier: Programming Language :: Python
Classifier: Programming Language :: Python :: 2.7
Classifier: Topic :: Utilities
